chatplayground/.gitignore
chatplayground/__init__.py
chatplayground/app/__init__.py
chatplayground/app/app.py
chatplayground/assets/favicon.ico
chatplayground/assets/react-json-view-lite.css
chatplayground/message_threads/faust_in_oxford_1683330128.209918.json
chatplayground/pcconfig.py
chatplayground-1.2.0.dist-info/LICENSE
chatplayground-1.2.0.dist-info/METADATA
chatplayground-1.2.0.dist-info/WHEEL
chatplayground-1.2.0.dist-info/entry_points.txt
chatplayground-1.2.0.dist-info/RECORD
