Metadata-Version: 2.1
Name: chatplayground
Version: 1.2.0
Summary: ChatPlayground for LLMs
Home-page: https://github.com/blackhc/chatplayground
License: GPL-3.0-only
Author: Andreas Kirsch
Author-email: blackhc@gmail.com
Requires-Python: >=3.10,<4.0
Classifier: Development Status :: 4 - Beta
Classifier: Intended Audience :: Developers
Classifier: License :: OSI Approved :: GNU General Public License v3 (GPLv3)
Classifier: Natural Language :: English
Classifier: Programming Language :: Python :: 3
Classifier: Programming Language :: Python :: 3.10
Classifier: Programming Language :: Python :: 3.11
Provides-Extra: dev
Provides-Extra: doc
Provides-Extra: test
Requires-Dist: black (>=22.12.0,<23.0.0) ; extra == "test"
Requires-Dist: bump2version (>=1.0.1,<2.0.0) ; extra == "dev"
Requires-Dist: click (==8.0.1)
Requires-Dist: flake8 (>=6.0.0,<7.0.0) ; extra == "test"
Requires-Dist: flake8-docstrings (>=1.6.0,<2.0.0) ; extra == "test"
Requires-Dist: ipykernel (>=6.19.2,<7.0.0) ; extra == "dev"
Requires-Dist: isort (>=5.8.0,<6.0.0) ; extra == "test"
Requires-Dist: langchain (>=0.0.137,<0.0.138)
Requires-Dist: manifest-ml (>=0.0.1,<0.0.2)
Requires-Dist: markdown (<3.4)
Requires-Dist: mkdocs (>=1.4.2,<2.0.0) ; extra == "doc"
Requires-Dist: mkdocs-autorefs (>=0.4.1,<0.5.0) ; extra == "doc"
Requires-Dist: mkdocs-include-markdown-plugin (>=1.0.0,<2.0.0) ; extra == "doc"
Requires-Dist: mkdocs-material (>=6.1.7,<7.0.0) ; extra == "doc"
Requires-Dist: mkdocs-material-extensions (>=1.1.1,<2.0.0)
Requires-Dist: mkdocstrings[python] (>=0.19.0,<0.20.0) ; extra == "doc"
Requires-Dist: mypy (>=1.1.1,<2.0.0) ; extra == "test"
Requires-Dist: openai (>=0.27.4,<0.28.0)
Requires-Dist: pip (>=22.3.1,<23.0.0) ; extra == "dev"
Requires-Dist: pre-commit (>=2.12.0,<3.0.0) ; extra == "dev"
Requires-Dist: protobuf (>=3.20.0,<3.21.0)
Requires-Dist: pydantic (>=1.10.2,<2.0.0)
Requires-Dist: pynecone (==0.1.27)
Requires-Dist: pytest (>=6.2.4,<7.0.0) ; extra == "test"
Requires-Dist: pytest-cov (>=2.12.0,<3.0.0) ; extra == "test"
Requires-Dist: toml (>=0.10.2,<0.11.0) ; extra == "dev"
Requires-Dist: tox (>=3.20.1,<4.0.0) ; extra == "dev"
Requires-Dist: twine (>=3.3.0,<4.0.0) ; extra == "dev"
Requires-Dist: watchdog (==2.3.1)
